{
  "session": 30,
  "region": "C2:8000-9000",
  "manifests": [
    {
      "pass": 1200,
      "address": 167083,
      "bank": 2,
      "label": "ct_c2_8cab_handler_s30",
      "range": "C2:8CAB-C2:8D11",
      "score": 9,
      "width": 102,
      "call_count": 7,
      "branch_count": 5,
      "stackish_count": 2,
      "return_count": 1,
      "session": 30,
      "rationale": "Score-9 function in 8C00-9000 region. 102 bytes, 7 internal calls. High-value handler."
    },
    {
      "pass": 1201,
      "address": 167303,
      "bank": 2,
      "label": "ct_c2_8d87_service_s30",
      "range": "C2:8D87-C2:8DDA",
      "score": 9,
      "width": 83,
      "call_count": 4,
      "branch_count": 3,
      "stackish_count": 2,
      "return_count": 1,
      "session": 30,
      "rationale": "Score-9 service function. 83 bytes, 4 calls. Strong boundaries."
    },
    {
      "pass": 1202,
      "address": 167614,
      "bank": 2,
      "label": "ct_c2_8ebe_handler_s30",
      "range": "C2:8EBE-C2:8F30",
      "score": 9,
      "width": 114,
      "call_count": 7,
      "branch_count": 4,
      "stackish_count": 3,
      "return_count": 1,
      "session": 30,
      "rationale": "Score-9 handler in 8E00-9000 region. 114 bytes, 7 calls."
    },
    {
      "pass": 1203,
      "address": 167728,
      "bank": 2,
      "label": "ct_c2_8f30_routine_s30",
      "range": "C2:8F30-C2:8F8E",
      "score": 9,
      "width": 94,
      "call_count": 6,
      "branch_count": 4,
      "stackish_count": 2,
      "return_count": 1,
      "session": 30,
      "rationale": "Score-9 routine. 94 bytes, 6 calls. Part of 8F00 hub network."
    },
    {
      "pass": 1204,
      "address": 167822,
      "bank": 2,
      "label": "ct_c2_8f8e_service_s30",
      "range": "C2:8F8E-C2:8FF9",
      "score": 9,
      "width": 107,
      "call_count": 5,
      "branch_count": 4,
      "stackish_count": 2,
      "return_count": 1,
      "session": 30,
      "rationale": "Score-9 service. 107 bytes, 5 calls. Near bank boundary."
    },
    {
      "pass": 1205,
      "address": 164258,
      "bank": 2,
      "label": "ct_c2_81a2_interrupt_s30",
      "range": "C2:81A2-C2:81EF",
      "score": 7,
      "width": 77,
      "call_count": 9,
      "branch_count": 6,
      "stackish_count": 2,
      "return_count": 1,
      "session": 30,
      "rationale": "Score-7 interrupt handler. 77 bytes, 9 calls, RTI return. 8100 region."
    },
    {
      "pass": 1206,
      "address": 165616,
      "bank": 2,
      "label": "ct_c2_86f0_handler_s30",
      "range": "C2:86F0-C2:875B",
      "score": 7,
      "width": 107,
      "call_count": 9,
      "branch_count": 5,
      "stackish_count": 3,
      "return_count": 1,
      "session": 30,
      "rationale": "Score-7 handler. 107 bytes, 9 calls. Rich subroutine."
    },
    {
      "pass": 1207,
      "address": 166160,
      "bank": 2,
      "label": "ct_c2_8910_mega_handler_s30",
      "range": "C2:8910-C2:89B9",
      "score": 7,
      "width": 169,
      "call_count": 12,
      "branch_count": 8,
      "stackish_count": 4,
      "return_count": 1,
      "session": 30,
      "rationale": "Score-7 mega-handler. 169 bytes, 12 calls! Largest in session. 8900 region."
    },
    {
      "pass": 1208,
      "address": 166710,
      "bank": 2,
      "label": "ct_c2_8b36_complex_s30",
      "range": "C2:8B36-C2:8CA7",
      "score": 7,
      "width": 369,
      "call_count": 15,
      "branch_count": 12,
      "stackish_count": 5,
      "return_count": 1,
      "session": 30,
      "rationale": "Score-7 complex function. 369 bytes, 15 calls! Massive handler. 8B00 region."
    },
    {
      "pass": 1209,
      "address": 165749,
      "bank": 2,
      "label": "ct_c2_8775_service_s30",
      "range": "C2:8775-C2:87B9",
      "score": 7,
      "width": 68,
      "call_count": 4,
      "branch_count": 3,
      "stackish_count": 2,
      "return_count": 1,
      "session": 30,
      "rationale": "Score-7 service function. 68 bytes, 4 calls. 8700 region coverage."
    },
    {
      "pass": 1210,
      "address": 165817,
      "bank": 2,
      "label": "ct_c2_87b9_helper_s30",
      "range": "C2:87B9-C2:8805",
      "score": 7,
      "width": 76,
      "call_count": 4,
      "branch_count": 3,
      "stackish_count": 2,
      "return_count": 1,
      "session": 30,
      "rationale": "Score-7 helper function. 76 bytes, 4 calls. 87B0-8800 region."
    },
    {
      "pass": 1211,
      "address": 165893,
      "bank": 2,
      "label": "ct_c2_8805_routine_s30",
      "range": "C2:8805-C2:8851",
      "score": 7,
      "width": 76,
      "call_count": 4,
      "branch_count": 3,
      "stackish_count": 2,
      "return_count": 1,
      "session": 30,
      "rationale": "Score-7 routine. 76 bytes, 4 calls. 8800-8900 transition region."
    }
  ],
  "total_bytes": 1442,
  "manifest_count": 12,
  "score_9_count": 5,
  "score_7_count": 7
}