[
  {
    "region": "0000-3000",
    "range": "C4:0E7A..C4:0E92",
    "score": 6,
    "calls": 1,
    "branches": 0,
    "width": 25,
    "start": "C4:0E7A"
  },
  {
    "region": "0000-3000",
    "range": "C4:0E7E..C4:0E96",
    "score": 6,
    "calls": 1,
    "branches": 0,
    "width": 25,
    "start": "C4:0E7E"
  },
  {
    "region": "0000-3000",
    "range": "C4:1701..C4:1708",
    "score": 6,
    "calls": 1,
    "branches": 2,
    "width": 8,
    "start": "C4:1701"
  },
  {
    "region": "0000-3000",
    "range": "C4:24F6..C4:24FD",
    "score": 6,
    "calls": 1,
    "branches": 0,
    "width": 8,
    "start": "C4:24F6"
  },
  {
    "region": "4000-5000",
    "range": "C4:46B7..C4:46CF",
    "score": 6,
    "calls": 1,
    "branches": 3,
    "width": 25,
    "start": "C4:46B7"
  },
  {
    "region": "6000-7000",
    "range": "C4:607A..C4:6085",
    "score": 6,
    "calls": 1,
    "branches": 1,
    "width": 12,
    "start": "C4:607A"
  },
  {
    "region": "6000-7000",
    "range": "C4:6BDA..C4:6BE1",
    "score": 6,
    "calls": 1,
    "branches": 0,
    "width": 8,
    "start": "C4:6BDA"
  },
  {
    "region": "8000-C000",
    "range": "C4:9DE6..C4:9DF6",
    "score": 6,
    "calls": 1,
    "branches": 1,
    "width": 17,
    "start": "C4:9DE6"
  },
  {
    "region": "8000-C000",
    "range": "C4:9E50..C4:9E56",
    "score": 6,
    "calls": 1,
    "branches": 2,
    "width": 7,
    "start": "C4:9E50"
  },
  {
    "region": "C000-FFFF",
    "range": "C4:C771..C4:C77C",
    "score": 6,
    "calls": 1,
    "branches": 1,
    "width": 12,
    "start": "C4:C771"
  }
]