{
  "range": "DE:0000..DE:4000",
  "island_count": 55,
  "cluster_count": 37,
  "islands": [
    {
      "range": "DE:1E20..DE:1E2B",
      "score": 5,
      "width": 12,
      "call_count": 0,
      "branch_count": 1,
      "stackish_count": 2,
      "return_count": 2,
      "first_return_address": "DE:1E29",
      "ascii_ratio": 0.25,
      "repeated_pair_score": 0.0,
      "data_misread_flags": []
    },
    {
      "range": "DE:0890..DE:0899",
      "score": 5,
      "width": 10,
      "call_count": 1,
      "branch_count": 0,
      "stackish_count": 0,
      "return_count": 1,
      "first_return_address": "DE:0899",
      "ascii_ratio": 0.2,
      "repeated_pair_score": 0.0,
      "data_misread_flags": []
    },
    {
      "range": "DE:1E20..DE:1E29",
      "score": 5,
      "width": 10,
      "call_count": 0,
      "branch_count": 1,
      "stackish_count": 2,
      "return_count": 1,
      "first_return_address": "DE:1E29",
      "ascii_ratio": 0.1,
      "repeated_pair_score": 0.0,
      "data_misread_flags": []
    },
    {
      "range": "DE:0864..DE:0873",
      "score": 4,
      "width": 16,
      "call_count": 0,
      "branch_count": 2,
      "stackish_count": 0,
      "return_count": 4,
      "first_return_address": "DE:0865",
      "ascii_ratio": 0.25,
      "repeated_pair_score": 0.0,
      "data_misread_flags": []
    },
    {
      "range": "DE:25DC..DE:25EB",
      "score": 4,
      "width": 16,
      "call_count": 1,
      "branch_count": 1,
      "stackish_count": 0,
      "return_count": 2,
      "first_return_address": "DE:25E9",
      "ascii_ratio": 0.875,
      "repeated_pair_score": 0.0,
      "data_misread_flags": []
    },
    {
      "range": "DE:0864..DE:0871",
      "score": 4,
      "width": 14,
      "call_count": 0,
      "branch_count": 2,
      "stackish_count": 0,
      "return_count": 3,
      "first_return_address": "DE:0865",
      "ascii_ratio": 0.214,
      "repeated_pair_score": 0.0,
      "data_misread_flags": []
    },
    {
      "range": "DE:2484..DE:2491",
      "score": 4,
      "width": 14,
      "call_count": 0,
      "branch_count": 2,
      "stackish_count": 0,
      "return_count": 1,
      "first_return_address": "DE:2491",
      "ascii_ratio": 0.214,
      "repeated_pair_score": 0.0,
      "data_misread_flags": []
    },
    {
      "range": "DE:25DC..DE:25E9",
      "score": 4,
      "width": 14,
      "call_count": 1,
      "branch_count": 1,
      "stackish_count": 0,
      "return_count": 1,
      "first_return_address": "DE:25E9",
      "ascii_ratio": 0.857,
      "repeated_pair_score": 0.0,
      "data_misread_flags": []
    },
    {
      "range": "DE:0B9E..DE:0BA3",
      "score": 4,
      "width": 6,
      "call_count": 1,
      "branch_count": 0,
      "stackish_count": 1,
      "return_count": 2,
      "first_return_address": "DE:0BA1",
      "ascii_ratio": 1.0,
      "repeated_pair_score": 0.0,
      "data_misread_flags": []
    },
    {
      "range": "DE:2044..DE:2049",
      "score": 4,
      "width": 6,
      "call_count": 0,
      "branch_count": 1,
      "stackish_count": 0,
      "return_count": 1,
      "first_return_address": "DE:2049",
      "ascii_ratio": 0.167,
      "repeated_pair_score": 0.0,
      "data_misread_flags": []
    },
    {
      "range": "DE:211D..DE:2121",
      "score": 4,
      "width": 5,
      "call_count": 0,
      "branch_count": 1,
      "stackish_count": 0,
      "return_count": 1,
      "first_return_address": "DE:2121",
      "ascii_ratio": 0.2,
      "repeated_pair_score": 0.0,
      "data_misread_flags": []
    },
    {
      "range": "DE:2E65..DE:2E69",
      "score": 4,
      "width": 5,
      "call_count": 0,
      "branch_count": 3,
      "stackish_count": 0,
      "return_count": 1,
      "first_return_address": "DE:2E69",
      "ascii_ratio": 0.2,
      "repeated_pair_score": 0.0,
      "data_misread_flags": []
    },
    {
      "range": "DE:2E8D..DE:2E91",
      "score": 4,
      "width": 5,
      "call_count": 0,
      "branch_count": 3,
      "stackish_count": 0,
      "return_count": 1,
      "first_return_address": "DE:2E91",
      "ascii_ratio": 0.2,
      "repeated_pair_score": 0.0,
      "data_misread_flags": []
    },
    {
      "range": "DE:2EB5..DE:2EB9",
      "score": 4,
      "width": 5,
      "call_count": 0,
      "branch_count": 3,
      "stackish_count": 0,
      "return_count": 1,
      "first_return_address": "DE:2EB9",
      "ascii_ratio": 0.2,
      "repeated_pair_score": 0.0,
      "data_misread_flags": []
    },
    {
      "range": "DE:2EDD..DE:2EE1",
      "score": 4,
      "width": 5,
      "call_count": 0,
      "branch_count": 3,
      "stackish_count": 0,
      "return_count": 1,
      "first_return_address": "DE:2EE1",
      "ascii_ratio": 0.2,
      "repeated_pair_score": 0.0,
      "data_misread_flags": []
    },
    {
      "range": "DE:3405..DE:3409",
      "score": 4,
      "width": 5,
      "call_count": 0,
      "branch_count": 3,
      "stackish_count": 0,
      "return_count": 1,
      "first_return_address": "DE:3409",
      "ascii_ratio": 0.2,
      "repeated_pair_score": 0.0,
      "data_misread_flags": []
    },
    {
      "range": "DE:0B86..DE:0B93",
      "score": 3,
      "width": 14,
      "call_count": 1,
      "branch_count": 0,
      "stackish_count": 0,
      "return_count": 3,
      "first_return_address": "DE:0B87",
      "ascii_ratio": 0.429,
      "repeated_pair_score": 0.0,
      "data_misread_flags": []
    },
    {
      "range": "DE:0890..DE:089B",
      "score": 3,
      "width": 12,
      "call_count": 1,
      "branch_count": 0,
      "stackish_count": 0,
      "return_count": 2,
      "first_return_address": "DE:0899",
      "ascii_ratio": 0.333,
      "repeated_pair_score": 0.0,
      "data_misread_flags": []
    },
    {
      "range": "DE:0B86..DE:0B91",
      "score": 3,
      "width": 12,
      "call_count": 1,
      "branch_count": 0,
      "stackish_count": 0,
      "return_count": 2,
      "first_return_address": "DE:0B87",
      "ascii_ratio": 0.333,
      "repeated_pair_score": 0.0,
      "data_misread_flags": []
    },
    {
      "range": "DE:2F50..DE:2F5B",
      "score": 3,
      "width": 12,
      "call_count": 0,
      "branch_count": 0,
      "stackish_count": 0,
      "return_count": 2,
      "first_return_address": "DE:2F59",
      "ascii_ratio": 0.167,
      "repeated_pair_score": 0.0,
      "data_misread_flags": []
    },
    {
      "range": "DE:3090..DE:309B",
      "score": 3,
      "width": 12,
      "call_count": 0,
      "branch_count": 0,
      "stackish_count": 0,
      "return_count": 2,
      "first_return_address": "DE:3099",
      "ascii_ratio": 0.167,
      "repeated_pair_score": 0.0,
      "data_misread_flags": []
    },
    {
      "range": "DE:19BF..DE:19C8",
      "score": 3,
      "width": 10,
      "call_count": 0,
      "branch_count": 0,
      "stackish_count": 0,
      "return_count": 2,
      "first_return_address": "DE:19BF",
      "ascii_ratio": 0.2,
      "repeated_pair_score": 0.0,
      "data_misread_flags": []
    },
    {
      "range": "DE:2F50..DE:2F59",
      "score": 3,
      "width": 10,
      "call_count": 0,
      "branch_count": 0,
      "stackish_count": 0,
      "return_count": 1,
      "first_return_address": "DE:2F59",
      "ascii_ratio": 0.1,
      "repeated_pair_score": 0.0,
      "data_misread_flags": []
    },
    {
      "range": "DE:3090..DE:3099",
      "score": 3,
      "width": 10,
      "call_count": 0,
      "branch_count": 0,
      "stackish_count": 0,
      "return_count": 1,
      "first_return_address": "DE:3099",
      "ascii_ratio": 0.1,
      "repeated_pair_score": 0.0,
      "data_misread_flags": []
    },
    {
      "range": "DE:2691..DE:2699",
      "score": 3,
      "width": 9,
      "call_count": 0,
      "branch_count": 3,
      "stackish_count": 1,
      "return_count": 1,
      "first_return_address": "DE:2699",
      "ascii_ratio": 0.222,
      "repeated_pair_score": 0.0,
      "data_misread_flags": [
        "sed_decimal_mode_at_03"
      ]
    },
    {
      "range": "DE:30AF..DE:30B3",
      "score": 3,
      "width": 5,
      "call_count": 1,
      "branch_count": 0,
      "stackish_count": 0,
      "return_count": 3,
      "first_return_address": "DE:30AF",
      "ascii_ratio": 1.0,
      "repeated_pair_score": 0.0,
      "data_misread_flags": []
    },
    {
      "range": "DE:30D7..DE:30DB",
      "score": 3,
      "width": 5,
      "call_count": 1,
      "branch_count": 0,
      "stackish_count": 0,
      "return_count": 3,
      "first_return_address": "DE:30D7",
      "ascii_ratio": 1.0,
      "repeated_pair_score": 0.0,
      "data_misread_flags": []
    },
    {
      "range": "DE:30B5..DE:30C3",
      "score": 2,
      "width": 15,
      "call_count": 0,
      "branch_count": 1,
      "stackish_count": 0,
      "return_count": 4,
      "first_return_address": "DE:30B5",
      "ascii_ratio": 0.333,
      "repeated_pair_score": 0.0,
      "data_misread_flags": []
    },
    {
      "range": "DE:0906..DE:0913",
      "score": 2,
      "width": 14,
      "call_count": 0,
      "branch_count": 2,
      "stackish_count": 0,
      "return_count": 2,
      "first_return_address": "DE:0911",
      "ascii_ratio": 0.143,
      "repeated_pair_score": 0.0,
      "data_misread_flags": [
        "sed_decimal_mode_at_00"
      ]
    },
    {
      "range": "DE:2E34..DE:2E41",
      "score": 2,
      "width": 14,
      "call_count": 1,
      "branch_count": 0,
      "stackish_count": 2,
      "return_count": 3,
      "first_return_address": "DE:2E35",
      "ascii_ratio": 0.357,
      "repeated_pair_score": 0.0,
      "data_misread_flags": [
        "sed_decimal_mode_at_06"
      ]
    },
    {
      "range": "DE:0A1E..DE:0A2A",
      "score": 2,
      "width": 13,
      "call_count": 0,
      "branch_count": 2,
      "stackish_count": 0,
      "return_count": 2,
      "first_return_address": "DE:0A1F",
      "ascii_ratio": 0.385,
      "repeated_pair_score": 0.0,
      "data_misread_flags": []
    },
    {
      "range": "DE:30B5..DE:30C1",
      "score": 2,
      "width": 13,
      "call_count": 0,
      "branch_count": 1,
      "stackish_count": 0,
      "return_count": 3,
      "first_return_address": "DE:30B5",
      "ascii_ratio": 0.308,
      "repeated_pair_score": 0.0,
      "data_misread_flags": []
    },
    {
      "range": "DE:362F..DE:363B",
      "score": 2,
      "width": 13,
      "call_count": 0,
      "branch_count": 0,
      "stackish_count": 1,
      "return_count": 3,
      "first_return_address": "DE:362F",
      "ascii_ratio": 0.231,
      "repeated_pair_score": 0.0,
      "data_misread_flags": [
        "sed_decimal_mode_at_01"
      ]
    },
    {
      "range": "DE:0906..DE:0911",
      "score": 2,
      "width": 12,
      "call_count": 0,
      "branch_count": 2,
      "stackish_count": 0,
      "return_count": 1,
      "first_return_address": "DE:0911",
      "ascii_ratio": 0.083,
      "repeated_pair_score": 0.0,
      "data_misread_flags": [
        "sed_decimal_mode_at_00"
      ]
    },
    {
      "range": "DE:3360..DE:336B",
      "score": 2,
      "width": 12,
      "call_count": 0,
      "branch_count": 0,
      "stackish_count": 1,
      "return_count": 2,
      "first_return_address": "DE:3369",
      "ascii_ratio": 0.167,
      "repeated_pair_score": 0.0,
      "data_misread_flags": [
        "sed_decimal_mode_at_00"
      ]
    },
    {
      "range": "DE:362F..DE:3639",
      "score": 2,
      "width": 11,
      "call_count": 0,
      "branch_count": 0,
      "stackish_count": 1,
      "return_count": 2,
      "first_return_address": "DE:362F",
      "ascii_ratio": 0.182,
      "repeated_pair_score": 0.0,
      "data_misread_flags": [
        "sed_decimal_mode_at_01"
      ]
    },
    {
      "range": "DE:2078..DE:2081",
      "score": 2,
      "width": 10,
      "call_count": 0,
      "branch_count": 2,
      "stackish_count": 0,
      "return_count": 1,
      "first_return_address": "DE:2081",
      "ascii_ratio": 0.1,
      "repeated_pair_score": 0.0,
      "data_misread_flags": [
        "sed_decimal_mode_at_04"
      ]
    },
    {
      "range": "DE:3360..DE:3369",
      "score": 2,
      "width": 10,
      "call_count": 0,
      "branch_count": 0,
      "stackish_count": 1,
      "return_count": 1,
      "first_return_address": "DE:3369",
      "ascii_ratio": 0.1,
      "repeated_pair_score": 0.0,
      "data_misread_flags": [
        "sed_decimal_mode_at_00"
      ]
    },
    {
      "range": "DE:36A6..DE:36AF",
      "score": 2,
      "width": 10,
      "call_count": 0,
      "branch_count": 0,
      "stackish_count": 2,
      "return_count": 5,
      "first_return_address": "DE:36A7",
      "ascii_ratio": 0.6,
      "repeated_pair_score": 0.0,
      "data_misread_flags": []
    },
    {
      "range": "DE:36F6..DE:36FF",
      "score": 2,
      "width": 10,
      "call_count": 0,
      "branch_count": 0,
      "stackish_count": 2,
      "return_count": 5,
      "first_return_address": "DE:36F7",
      "ascii_ratio": 0.6,
      "repeated_pair_score": 0.0,
      "data_misread_flags": []
    },
    {
      "range": "DE:36A6..DE:36AD",
      "score": 2,
      "width": 8,
      "call_count": 0,
      "branch_count": 0,
      "stackish_count": 2,
      "return_count": 4,
      "first_return_address": "DE:36A7",
      "ascii_ratio": 0.625,
      "repeated_pair_score": 0.0,
      "data_misread_flags": []
    },
    {
      "range": "DE:36F6..DE:36FD",
      "score": 2,
      "width": 8,
      "call_count": 0,
      "branch_count": 0,
      "stackish_count": 2,
      "return_count": 4,
      "first_return_address": "DE:36F7",
      "ascii_ratio": 0.625,
      "repeated_pair_score": 0.0,
      "data_misread_flags": []
    },
    {
      "range": "DE:32F5..DE:32FB",
      "score": 2,
      "width": 7,
      "call_count": 0,
      "branch_count": 0,
      "stackish_count": 1,
      "return_count": 3,
      "first_return_address": "DE:32F5",
      "ascii_ratio": 0.429,
      "repeated_pair_score": 0.0,
      "data_misread_flags": []
    },
    {
      "range": "DE:342D..DE:3433",
      "score": 2,
      "width": 7,
      "call_count": 0,
      "branch_count": 3,
      "stackish_count": 0,
      "return_count": 2,
      "first_return_address": "DE:3431",
      "ascii_ratio": 0.571,
      "repeated_pair_score": 0.0,
      "data_misread_flags": []
    },
    {
      "range": "DE:343D..DE:3443",
      "score": 2,
      "width": 7,
      "call_count": 0,
      "branch_count": 0,
      "stackish_count": 1,
      "return_count": 4,
      "first_return_address": "DE:343D",
      "ascii_ratio": 0.857,
      "repeated_pair_score": 0.0,
      "data_misread_flags": []
    },
    {
      "range": "DE:269C..DE:26A1",
      "score": 2,
      "width": 6,
      "call_count": 0,
      "branch_count": 0,
      "stackish_count": 1,
      "return_count": 3,
      "first_return_address": "DE:269D",
      "ascii_ratio": 1.0,
      "repeated_pair_score": 0.0,
      "data_misread_flags": []
    },
    {
      "range": "DE:26AC..DE:26B1",
      "score": 2,
      "width": 6,
      "call_count": 0,
      "branch_count": 0,
      "stackish_count": 1,
      "return_count": 3,
      "first_return_address": "DE:26AD",
      "ascii_ratio": 1.0,
      "repeated_pair_score": 0.0,
      "data_misread_flags": []
    },
    {
      "range": "DE:36A6..DE:36AB",
      "score": 2,
      "width": 6,
      "call_count": 0,
      "branch_count": 0,
      "stackish_count": 2,
      "return_count": 3,
      "first_return_address": "DE:36A7",
      "ascii_ratio": 0.667,
      "repeated_pair_score": 0.0,
      "data_misread_flags": []
    },
    {
      "range": "DE:36F6..DE:36FB",
      "score": 2,
      "width": 6,
      "call_count": 0,
      "branch_count": 0,
      "stackish_count": 2,
      "return_count": 3,
      "first_return_address": "DE:36F7",
      "ascii_ratio": 0.667,
      "repeated_pair_score": 0.0,
      "data_misread_flags": []
    },
    {
      "range": "DE:215B..DE:215F",
      "score": 2,
      "width": 5,
      "call_count": 0,
      "branch_count": 0,
      "stackish_count": 1,
      "return_count": 2,
      "first_return_address": "DE:215B",
      "ascii_ratio": 1.0,
      "repeated_pair_score": 0.0,
      "data_misread_flags": []
    },
    {
      "range": "DE:30A7..DE:30AB",
      "score": 2,
      "width": 5,
      "call_count": 0,
      "branch_count": 0,
      "stackish_count": 1,
      "return_count": 3,
      "first_return_address": "DE:30A7",
      "ascii_ratio": 0.6,
      "repeated_pair_score": 0.0,
      "data_misread_flags": []
    },
    {
      "range": "DE:32F5..DE:32F9",
      "score": 2,
      "width": 5,
      "call_count": 0,
      "branch_count": 0,
      "stackish_count": 1,
      "return_count": 2,
      "first_return_address": "DE:32F5",
      "ascii_ratio": 0.4,
      "repeated_pair_score": 0.0,
      "data_misread_flags": []
    },
    {
      "range": "DE:336F..DE:3373",
      "score": 2,
      "width": 5,
      "call_count": 0,
      "branch_count": 0,
      "stackish_count": 1,
      "return_count": 3,
      "first_return_address": "DE:336F",
      "ascii_ratio": 1.0,
      "repeated_pair_score": 0.0,
      "data_misread_flags": []
    },
    {
      "range": "DE:342D..DE:3431",
      "score": 2,
      "width": 5,
      "call_count": 0,
      "branch_count": 3,
      "stackish_count": 0,
      "return_count": 1,
      "first_return_address": "DE:3431",
      "ascii_ratio": 0.4,
      "repeated_pair_score": 0.0,
      "data_misread_flags": []
    },
    {
      "range": "DE:35F7..DE:35FB",
      "score": 2,
      "width": 5,
      "call_count": 0,
      "branch_count": 0,
      "stackish_count": 1,
      "return_count": 3,
      "first_return_address": "DE:35F7",
      "ascii_ratio": 1.0,
      "repeated_pair_score": 0.0,
      "data_misread_flags": []
    }
  ],
  "clusters": [
    {
      "range": "DE:1E20..DE:1E2B",
      "cluster_score": 6,
      "child_count": 2,
      "child_ranges": [
        "DE:1E20..DE:1E29",
        "DE:1E20..DE:1E2B"
      ],
      "width": 12,
      "call_count": 0,
      "branch_count": 1,
      "stackish_count": 2,
      "return_count": 2,
      "ascii_ratio": 0.25,
      "repeated_pair_score": 0.0,
      "data_misread_flags": []
    },
    {
      "range": "DE:0864..DE:0873",
      "cluster_score": 5,
      "child_count": 2,
      "child_ranges": [
        "DE:0864..DE:0871",
        "DE:0864..DE:0873"
      ],
      "width": 16,
      "call_count": 0,
      "branch_count": 2,
      "stackish_count": 0,
      "return_count": 4,
      "ascii_ratio": 0.25,
      "repeated_pair_score": 0.0,
      "data_misread_flags": []
    },
    {
      "range": "DE:25DC..DE:25EB",
      "cluster_score": 5,
      "child_count": 2,
      "child_ranges": [
        "DE:25DC..DE:25E9",
        "DE:25DC..DE:25EB"
      ],
      "width": 16,
      "call_count": 1,
      "branch_count": 1,
      "stackish_count": 0,
      "return_count": 2,
      "ascii_ratio": 0.875,
      "repeated_pair_score": 0.0,
      "data_misread_flags": []
    },
    {
      "range": "DE:30AF..DE:30C3",
      "cluster_score": 4,
      "child_count": 3,
      "child_ranges": [
        "DE:30AF..DE:30B3",
        "DE:30B5..DE:30C1",
        "DE:30B5..DE:30C3"
      ],
      "width": 21,
      "call_count": 1,
      "branch_count": 1,
      "stackish_count": 0,
      "return_count": 7,
      "ascii_ratio": 0.476,
      "repeated_pair_score": 0.0,
      "data_misread_flags": []
    },
    {
      "range": "DE:0B86..DE:0B93",
      "cluster_score": 4,
      "child_count": 2,
      "child_ranges": [
        "DE:0B86..DE:0B91",
        "DE:0B86..DE:0B93"
      ],
      "width": 14,
      "call_count": 1,
      "branch_count": 0,
      "stackish_count": 0,
      "return_count": 3,
      "ascii_ratio": 0.429,
      "repeated_pair_score": 0.0,
      "data_misread_flags": []
    },
    {
      "range": "DE:2484..DE:2491",
      "cluster_score": 4,
      "child_count": 1,
      "child_ranges": [
        "DE:2484..DE:2491"
      ],
      "width": 14,
      "call_count": 0,
      "branch_count": 2,
      "stackish_count": 0,
      "return_count": 1,
      "ascii_ratio": 0.214,
      "repeated_pair_score": 0.0,
      "data_misread_flags": []
    },
    {
      "range": "DE:0890..DE:089B",
      "cluster_score": 4,
      "child_count": 2,
      "child_ranges": [
        "DE:0890..DE:0899",
        "DE:0890..DE:089B"
      ],
      "width": 12,
      "call_count": 1,
      "branch_count": 0,
      "stackish_count": 0,
      "return_count": 2,
      "ascii_ratio": 0.333,
      "repeated_pair_score": 0.0,
      "data_misread_flags": []
    },
    {
      "range": "DE:2F50..DE:2F5B",
      "cluster_score": 4,
      "child_count": 2,
      "child_ranges": [
        "DE:2F50..DE:2F59",
        "DE:2F50..DE:2F5B"
      ],
      "width": 12,
      "call_count": 0,
      "branch_count": 0,
      "stackish_count": 0,
      "return_count": 2,
      "ascii_ratio": 0.167,
      "repeated_pair_score": 0.0,
      "data_misread_flags": []
    },
    {
      "range": "DE:3090..DE:309B",
      "cluster_score": 4,
      "child_count": 2,
      "child_ranges": [
        "DE:3090..DE:3099",
        "DE:3090..DE:309B"
      ],
      "width": 12,
      "call_count": 0,
      "branch_count": 0,
      "stackish_count": 0,
      "return_count": 2,
      "ascii_ratio": 0.167,
      "repeated_pair_score": 0.0,
      "data_misread_flags": []
    },
    {
      "range": "DE:36A6..DE:36AF",
      "cluster_score": 4,
      "child_count": 3,
      "child_ranges": [
        "DE:36A6..DE:36AB",
        "DE:36A6..DE:36AD",
        "DE:36A6..DE:36AF"
      ],
      "width": 10,
      "call_count": 0,
      "branch_count": 0,
      "stackish_count": 2,
      "return_count": 5,
      "ascii_ratio": 0.6,
      "repeated_pair_score": 0.0,
      "data_misread_flags": []
    },
    {
      "range": "DE:36F6..DE:36FF",
      "cluster_score": 4,
      "child_count": 3,
      "child_ranges": [
        "DE:36F6..DE:36FB",
        "DE:36F6..DE:36FD",
        "DE:36F6..DE:36FF"
      ],
      "width": 10,
      "call_count": 0,
      "branch_count": 0,
      "stackish_count": 2,
      "return_count": 5,
      "ascii_ratio": 0.6,
      "repeated_pair_score": 0.0,
      "data_misread_flags": []
    },
    {
      "range": "DE:0B9E..DE:0BA3",
      "cluster_score": 4,
      "child_count": 1,
      "child_ranges": [
        "DE:0B9E..DE:0BA3"
      ],
      "width": 6,
      "call_count": 1,
      "branch_count": 0,
      "stackish_count": 1,
      "return_count": 2,
      "ascii_ratio": 1.0,
      "repeated_pair_score": 0.0,
      "data_misread_flags": []
    },
    {
      "range": "DE:2044..DE:2049",
      "cluster_score": 4,
      "child_count": 1,
      "child_ranges": [
        "DE:2044..DE:2049"
      ],
      "width": 6,
      "call_count": 0,
      "branch_count": 1,
      "stackish_count": 0,
      "return_count": 1,
      "ascii_ratio": 0.167,
      "repeated_pair_score": 0.0,
      "data_misread_flags": []
    },
    {
      "range": "DE:211D..DE:2121",
      "cluster_score": 4,
      "child_count": 1,
      "child_ranges": [
        "DE:211D..DE:2121"
      ],
      "width": 5,
      "call_count": 0,
      "branch_count": 1,
      "stackish_count": 0,
      "return_count": 1,
      "ascii_ratio": 0.2,
      "repeated_pair_score": 0.0,
      "data_misread_flags": []
    },
    {
      "range": "DE:2E65..DE:2E69",
      "cluster_score": 4,
      "child_count": 1,
      "child_ranges": [
        "DE:2E65..DE:2E69"
      ],
      "width": 5,
      "call_count": 0,
      "branch_count": 3,
      "stackish_count": 0,
      "return_count": 1,
      "ascii_ratio": 0.2,
      "repeated_pair_score": 0.0,
      "data_misread_flags": []
    },
    {
      "range": "DE:2E8D..DE:2E91",
      "cluster_score": 4,
      "child_count": 1,
      "child_ranges": [
        "DE:2E8D..DE:2E91"
      ],
      "width": 5,
      "call_count": 0,
      "branch_count": 3,
      "stackish_count": 0,
      "return_count": 1,
      "ascii_ratio": 0.2,
      "repeated_pair_score": 0.0,
      "data_misread_flags": []
    },
    {
      "range": "DE:2EB5..DE:2EB9",
      "cluster_score": 4,
      "child_count": 1,
      "child_ranges": [
        "DE:2EB5..DE:2EB9"
      ],
      "width": 5,
      "call_count": 0,
      "branch_count": 3,
      "stackish_count": 0,
      "return_count": 1,
      "ascii_ratio": 0.2,
      "repeated_pair_score": 0.0,
      "data_misread_flags": []
    },
    {
      "range": "DE:2EDD..DE:2EE1",
      "cluster_score": 4,
      "child_count": 1,
      "child_ranges": [
        "DE:2EDD..DE:2EE1"
      ],
      "width": 5,
      "call_count": 0,
      "branch_count": 3,
      "stackish_count": 0,
      "return_count": 1,
      "ascii_ratio": 0.2,
      "repeated_pair_score": 0.0,
      "data_misread_flags": []
    },
    {
      "range": "DE:3405..DE:3409",
      "cluster_score": 4,
      "child_count": 1,
      "child_ranges": [
        "DE:3405..DE:3409"
      ],
      "width": 5,
      "call_count": 0,
      "branch_count": 3,
      "stackish_count": 0,
      "return_count": 1,
      "ascii_ratio": 0.2,
      "repeated_pair_score": 0.0,
      "data_misread_flags": []
    },
    {
      "range": "DE:0906..DE:0913",
      "cluster_score": 3,
      "child_count": 2,
      "child_ranges": [
        "DE:0906..DE:0911",
        "DE:0906..DE:0913"
      ],
      "width": 14,
      "call_count": 0,
      "branch_count": 2,
      "stackish_count": 0,
      "return_count": 2,
      "ascii_ratio": 0.143,
      "repeated_pair_score": 0.0,
      "data_misread_flags": [
        "sed_decimal_mode_at_00"
      ]
    },
    {
      "range": "DE:362F..DE:363B",
      "cluster_score": 3,
      "child_count": 2,
      "child_ranges": [
        "DE:362F..DE:3639",
        "DE:362F..DE:363B"
      ],
      "width": 13,
      "call_count": 0,
      "branch_count": 0,
      "stackish_count": 1,
      "return_count": 3,
      "ascii_ratio": 0.231,
      "repeated_pair_score": 0.0,
      "data_misread_flags": [
        "sed_decimal_mode_at_01"
      ]
    },
    {
      "range": "DE:3360..DE:336B",
      "cluster_score": 3,
      "child_count": 2,
      "child_ranges": [
        "DE:3360..DE:3369",
        "DE:3360..DE:336B"
      ],
      "width": 12,
      "call_count": 0,
      "branch_count": 0,
      "stackish_count": 1,
      "return_count": 2,
      "ascii_ratio": 0.167,
      "repeated_pair_score": 0.0,
      "data_misread_flags": [
        "sed_decimal_mode_at_00"
      ]
    },
    {
      "range": "DE:19BF..DE:19C8",
      "cluster_score": 3,
      "child_count": 1,
      "child_ranges": [
        "DE:19BF..DE:19C8"
      ],
      "width": 10,
      "call_count": 0,
      "branch_count": 0,
      "stackish_count": 0,
      "return_count": 2,
      "ascii_ratio": 0.2,
      "repeated_pair_score": 0.0,
      "data_misread_flags": []
    },
    {
      "range": "DE:2691..DE:2699",
      "cluster_score": 3,
      "child_count": 1,
      "child_ranges": [
        "DE:2691..DE:2699"
      ],
      "width": 9,
      "call_count": 0,
      "branch_count": 3,
      "stackish_count": 1,
      "return_count": 1,
      "ascii_ratio": 0.222,
      "repeated_pair_score": 0.0,
      "data_misread_flags": [
        "sed_decimal_mode_at_03"
      ]
    },
    {
      "range": "DE:32F5..DE:32FB",
      "cluster_score": 3,
      "child_count": 2,
      "child_ranges": [
        "DE:32F5..DE:32F9",
        "DE:32F5..DE:32FB"
      ],
      "width": 7,
      "call_count": 0,
      "branch_count": 0,
      "stackish_count": 1,
      "return_count": 3,
      "ascii_ratio": 0.429,
      "repeated_pair_score": 0.0,
      "data_misread_flags": []
    },
    {
      "range": "DE:342D..DE:3433",
      "cluster_score": 3,
      "child_count": 2,
      "child_ranges": [
        "DE:342D..DE:3431",
        "DE:342D..DE:3433"
      ],
      "width": 7,
      "call_count": 0,
      "branch_count": 3,
      "stackish_count": 0,
      "return_count": 2,
      "ascii_ratio": 0.571,
      "repeated_pair_score": 0.0,
      "data_misread_flags": []
    },
    {
      "range": "DE:30D7..DE:30DB",
      "cluster_score": 3,
      "child_count": 1,
      "child_ranges": [
        "DE:30D7..DE:30DB"
      ],
      "width": 5,
      "call_count": 1,
      "branch_count": 0,
      "stackish_count": 0,
      "return_count": 3,
      "ascii_ratio": 1.0,
      "repeated_pair_score": 0.0,
      "data_misread_flags": []
    },
    {
      "range": "DE:2E34..DE:2E41",
      "cluster_score": 2,
      "child_count": 1,
      "child_ranges": [
        "DE:2E34..DE:2E41"
      ],
      "width": 14,
      "call_count": 1,
      "branch_count": 0,
      "stackish_count": 2,
      "return_count": 3,
      "ascii_ratio": 0.357,
      "repeated_pair_score": 0.0,
      "data_misread_flags": [
        "sed_decimal_mode_at_06"
      ]
    },
    {
      "range": "DE:0A1E..DE:0A2A",
      "cluster_score": 2,
      "child_count": 1,
      "child_ranges": [
        "DE:0A1E..DE:0A2A"
      ],
      "width": 13,
      "call_count": 0,
      "branch_count": 2,
      "stackish_count": 0,
      "return_count": 2,
      "ascii_ratio": 0.385,
      "repeated_pair_score": 0.0,
      "data_misread_flags": []
    },
    {
      "range": "DE:2078..DE:2081",
      "cluster_score": 2,
      "child_count": 1,
      "child_ranges": [
        "DE:2078..DE:2081"
      ],
      "width": 10,
      "call_count": 0,
      "branch_count": 2,
      "stackish_count": 0,
      "return_count": 1,
      "ascii_ratio": 0.1,
      "repeated_pair_score": 0.0,
      "data_misread_flags": [
        "sed_decimal_mode_at_04"
      ]
    },
    {
      "range": "DE:343D..DE:3443",
      "cluster_score": 2,
      "child_count": 1,
      "child_ranges": [
        "DE:343D..DE:3443"
      ],
      "width": 7,
      "call_count": 0,
      "branch_count": 0,
      "stackish_count": 1,
      "return_count": 4,
      "ascii_ratio": 0.857,
      "repeated_pair_score": 0.0,
      "data_misread_flags": []
    },
    {
      "range": "DE:269C..DE:26A1",
      "cluster_score": 2,
      "child_count": 1,
      "child_ranges": [
        "DE:269C..DE:26A1"
      ],
      "width": 6,
      "call_count": 0,
      "branch_count": 0,
      "stackish_count": 1,
      "return_count": 3,
      "ascii_ratio": 1.0,
      "repeated_pair_score": 0.0,
      "data_misread_flags": []
    },
    {
      "range": "DE:26AC..DE:26B1",
      "cluster_score": 2,
      "child_count": 1,
      "child_ranges": [
        "DE:26AC..DE:26B1"
      ],
      "width": 6,
      "call_count": 0,
      "branch_count": 0,
      "stackish_count": 1,
      "return_count": 3,
      "ascii_ratio": 1.0,
      "repeated_pair_score": 0.0,
      "data_misread_flags": []
    },
    {
      "range": "DE:215B..DE:215F",
      "cluster_score": 2,
      "child_count": 1,
      "child_ranges": [
        "DE:215B..DE:215F"
      ],
      "width": 5,
      "call_count": 0,
      "branch_count": 0,
      "stackish_count": 1,
      "return_count": 2,
      "ascii_ratio": 1.0,
      "repeated_pair_score": 0.0,
      "data_misread_flags": []
    },
    {
      "range": "DE:30A7..DE:30AB",
      "cluster_score": 2,
      "child_count": 1,
      "child_ranges": [
        "DE:30A7..DE:30AB"
      ],
      "width": 5,
      "call_count": 0,
      "branch_count": 0,
      "stackish_count": 1,
      "return_count": 3,
      "ascii_ratio": 0.6,
      "repeated_pair_score": 0.0,
      "data_misread_flags": []
    },
    {
      "range": "DE:336F..DE:3373",
      "cluster_score": 2,
      "child_count": 1,
      "child_ranges": [
        "DE:336F..DE:3373"
      ],
      "width": 5,
      "call_count": 0,
      "branch_count": 0,
      "stackish_count": 1,
      "return_count": 3,
      "ascii_ratio": 1.0,
      "repeated_pair_score": 0.0,
      "data_misread_flags": []
    },
    {
      "range": "DE:35F7..DE:35FB",
      "cluster_score": 2,
      "child_count": 1,
      "child_ranges": [
        "DE:35F7..DE:35FB"
      ],
      "width": 5,
      "call_count": 0,
      "branch_count": 0,
      "stackish_count": 1,
      "return_count": 3,
      "ascii_ratio": 1.0,
      "repeated_pair_score": 0.0,
      "data_misread_flags": []
    }
  ]
}
